tiingo_client/__init__.py
tiingo_client/client.py
tiingo_client/util.py
tiingo_client-0.1.0.dist-info/LICENSE
tiingo_client-0.1.0.dist-info/WHEEL
tiingo_client-0.1.0.dist-info/METADATA
tiingo_client-0.1.0.dist-info/RECORD
