Metadata-Version: 2.1
Name: tiingo-client
Version: 0.1.0
Summary: 
Author: Andrew Rainboldt
Author-email: arainboldt@protonmail.com
Requires-Python: >=3.8,<4.0
Classifier: Programming Language :: Python :: 3
Classifier: Programming Language :: Python :: 3.8
Classifier: Programming Language :: Python :: 3.9
Requires-Dist: async-mixin (==0.0.2)
Requires-Dist: pandas (>=1.3.5,<2.0.0)
